eventapi/EventApi.py
eventapi/Exceptions.py
eventapi/WebSocket.py
eventapi/__init__.py
eventapi-1.1.2.dist-info/LICENSE
eventapi-1.1.2.dist-info/METADATA
eventapi-1.1.2.dist-info/WHEEL
eventapi-1.1.2.dist-info/top_level.txt
eventapi-1.1.2.dist-info/RECORD
