Metadata-Version: 2.1
Name: eventapi
Version: 1.1.2
Summary: Wrapper for 7TV EventAPI.
Home-page: https://github.com/yoggys/eventapi
Author: yoggys
Author-email: yoggies@yoggies.dev
Keywords: python,7tv,eventapi,7tvapi,7tveventapi,async,asyncio,wrapper
Classifier: Development Status :: 4 - Beta
Classifier: Intended Audience :: Developers
Classifier: License :: OSI Approved :: MIT License
Classifier: Programming Language :: Python :: 3
Classifier: Programming Language :: Python :: 3.8
Classifier: Programming Language :: Python :: 3.9
Classifier: Programming Language :: Python :: 3.10
Classifier: Programming Language :: Python :: 3.11
Classifier: Programming Language :: Python :: 3.12
License-File: LICENSE
Requires-Dist: websockets ~=12.0
Requires-Dist: typing-extensions ~=4.12.2
